{
  "blogs": [
    {
      "title": "Modern HTML Explained For Dinosaurs",
      "author": "Peter Jang",
      "url": "https://medium.com/actualize-network/modern-html-explained-for-dinosaurs-65e56af2981",
      "likes": 500,
      "user": "5f2cb9403bdbab46eccfb383",
      "id": "5f2cb9403bdbab46eccfb384"
    },
    {
      "title": "Modern CSS Explained For Dinosaurs",
      "author": "Peter Jang",
      "url": "https://medium.com/actualize-network/modern-css-explained-for-dinosaurs-5226febe3525",
      "likes": 25000,
      "user": "5f2cb9403bdbab46eccfb383",
      "id": "5f2cb9413bdbab46eccfb385"
    },
    {
      "title": "Learn react",
      "author": "React docs",
      "url": "https://medium.com/actualize-network/modern-css-explained-for-dinosaurs-5226febe3525",
      "likes": 25000,
      "user": "5f2cb9403bdbab46eccfb383",
      "id": "1111"
    },
    {
      "title": "danito",
      "author": "elijah",
      "likes": "elizalde",
      "url": "mito",
      "id": "EEYmNKp"
    },
    {
      "title": "",
      "author": "",
      "likes": "",
      "url": "",
      "id": "bjA6jCr"
    },
    {
      "title": "",
      "author": "",
      "likes": "",
      "url": "",
      "id": "ziZFGwX"
    },
    {
      "title": "",
      "author": "d",
      "likes": "",
      "url": "",
      "id": "ps_fW5W"
    },
    {
      "title": "",
      "author": "",
      "likes": "",
      "url": "",
      "id": "VQ0DRSv"
    },
    {
      "title": "",
      "author": "",
      "likes": "",
      "url": "",
      "id": "j7YYguZ"
    },
    {
      "title": "test",
      "author": "by",
      "likes": "000",
      "url": "www.pene.com",
      "id": "HUSt4pA"
    },
    {
      "title": "",
      "author": "",
      "likes": "",
      "url": "",
      "id": "403-1aG"
    },
    {
      "title": "",
      "author": "",
      "likes": "",
      "url": "",
      "id": "v_37AAb"
    },
    {
      "title": "",
      "author": "",
      "likes": "",
      "url": "",
      "id": "qYGMG43"
    },
    {
      "title": "",
      "author": "",
      "likes": "",
      "url": "",
      "id": "Vgsrb1O"
    }
  ]
}